{
  "cpu_samples": [
    {
      "timestamp": 1763267678.196339,
      "process_cpu": 55.42999999999999,
      "process_cpu_raw": 554.3,
      "percpu": [
        100.0,
        100.0,
        100.0,
        100.0,
        100.0,
        100.0,
        100.0,
        100.0,
        100.0,
        100.0
      ],
      "avg": 100.0,
      "sample_duration": 0.11294412612915039
    },
    {
      "timestamp": 1763267678.564474,
      "process_cpu": 59.17999999999999,
      "process_cpu_raw": 591.8,
      "percpu": [
        83.3,
        83.3,
        71.4,
        57.1,
        42.9,
        28.6,
        100.0,
        100.0,
        100.0,
        100.0
      ],
      "avg": 76.66,
      "sample_duration": 0.12028288841247559
    },
    {
      "timestamp": 1763267678.9430678,
      "process_cpu": 59.77,
      "process_cpu_raw": 597.7,
      "percpu": [
        100.0,
        83.3,
        66.7,
        60.0,
        0.0,
        16.7,
        100.0,
        83.3,
        100.0,
        100.0
      ],
      "avg": 71.0,
      "sample_duration": 0.10697340965270996
    },
    {
      "timestamp": 1763267679.3100889,
      "process_cpu": 58.870000000000005,
      "process_cpu_raw": 588.7,
      "percpu": [
        100.0,
        83.3,
        80.0,
        50.0,
        16.7,
        16.7,
        100.0,
        100.0,
        100.0,
        100.0
      ],
      "avg": 74.67,
      "sample_duration": 0.11073732376098633
    },
    {
      "timestamp": 1763267679.680195,
      "process_cpu": 56.120000000000005,
      "process_cpu_raw": 561.2,
      "percpu": [
        100.0,
        100.0,
        100.0,
        83.3,
        66.7,
        40.0,
        100.0,
        100.0,
        100.0,
        100.0
      ],
      "avg": 89.0,
      "sample_duration": 0.11763405799865723
    },
    {
      "timestamp": 1763267680.0538602,
      "process_cpu": 58.42,
      "process_cpu_raw": 584.2,
      "percpu": [
        85.7,
        83.3,
        66.7,
        57.1,
        33.3,
        16.7,
        100.0,
        100.0,
        100.0,
        100.0
      ],
      "avg": 74.28,
      "sample_duration": 0.1163778305053711
    },
    {
      "timestamp": 1763267680.426969,
      "process_cpu": 57.58,
      "process_cpu_raw": 575.8,
      "percpu": [
        100.0,
        83.3,
        71.4,
        66.7,
        20.0,
        14.3,
        100.0,
        100.0,
        100.0,
        100.0
      ],
      "avg": 75.57000000000001,
      "sample_duration": 0.11174893379211426
    },
    {
      "timestamp": 1763267680.79826,
      "process_cpu": 57.33,
      "process_cpu_raw": 573.3,
      "percpu": [
        100.0,
        80.0,
        75.0,
        40.0,
        20.0,
        0.0,
        100.0,
        100.0,
        100.0,
        100.0
      ],
      "avg": 71.5,
      "sample_duration": 0.1111140251159668
    },
    {
      "timestamp": 1763267681.1694,
      "process_cpu": 59.07000000000001,
      "process_cpu_raw": 590.7,
      "percpu": [
        100.0,
        80.0,
        100.0,
        100.0,
        100.0,
        80.0,
        100.0,
        100.0,
        100.0,
        100.0
      ],
      "avg": 96.0,
      "sample_duration": 0.10292887687683105
    },
    {
      "timestamp": 1763267681.5309062,
      "process_cpu": 58.260000000000005,
      "process_cpu_raw": 582.6,
      "percpu": [
        100.0,
        100.0,
        100.0,
        60.0,
        60.0,
        40.0,
        100.0,
        100.0,
        100.0,
        100.0
      ],
      "avg": 86.0,
      "sample_duration": 0.11456680297851562
    },
    {
      "timestamp": 1763267681.900774,
      "process_cpu": 58.42999999999999,
      "process_cpu_raw": 584.3,
      "percpu": [
        100.0,
        100.0,
        50.0,
        42.9,
        16.7,
        16.7,
        100.0,
        100.0,
        100.0,
        100.0
      ],
      "avg": 72.63,
      "sample_duration": 0.1174008846282959
    },
    {
      "timestamp": 1763267682.278225,
      "process_cpu": 57.46,
      "process_cpu_raw": 574.6,
      "percpu": [
        100.0,
        100.0,
        83.3,
        100.0,
        83.3,
        80.0,
        100.0,
        100.0,
        100.0,
        100.0
      ],
      "avg": 94.66,
      "sample_duration": 0.1184701919555664
    },
    {
      "timestamp": 1763267682.656533,
      "process_cpu": 57.42,
      "process_cpu_raw": 574.2,
      "percpu": [
        83.3,
        83.3,
        71.4,
        83.3,
        75.0,
        66.7,
        100.0,
        100.0,
        100.0,
        100.0
      ],
      "avg": 86.3,
      "sample_duration": 0.11567401885986328
    },
    {
      "timestamp": 1763267683.029835,
      "process_cpu": 59.48,
      "process_cpu_raw": 594.8,
      "percpu": [
        83.3,
        85.7,
        66.7,
        66.7,
        20.0,
        16.7,
        100.0,
        100.0,
        100.0,
        100.0
      ],
      "avg": 73.91,
      "sample_duration": 0.11678910255432129
    },
    {
      "timestamp": 1763267683.406655,
      "process_cpu": 58.89,
      "process_cpu_raw": 588.9,
      "percpu": [
        85.7,
        83.3,
        80.0,
        60.0,
        57.1,
        40.0,
        100.0,
        83.3,
        100.0,
        100.0
      ],
      "avg": 78.94,
      "sample_duration": 0.11181306838989258
    },
    {
      "timestamp": 1763267683.7748108,
      "process_cpu": 58.489999999999995,
      "process_cpu_raw": 584.9,
      "percpu": [
        100.0,
        100.0,
        80.0,
        50.0,
        25.0,
        0.0,
        100.0,
        100.0,
        100.0,
        100.0
      ],
      "avg": 75.5,
      "sample_duration": 0.10446739196777344
    },
    {
      "timestamp": 1763267684.1298728,
      "process_cpu": 58.239999999999995,
      "process_cpu_raw": 582.4,
      "percpu": [
        100.0,
        83.3,
        80.0,
        80.0,
        80.0,
        60.0,
        100.0,
        100.0,
        83.3,
        100.0
      ],
      "avg": 86.66,
      "sample_duration": 0.10737323760986328
    },
    {
      "timestamp": 1763267684.4955058,
      "process_cpu": 57.760000000000005,
      "process_cpu_raw": 577.6,
      "percpu": [
        100.0,
        100.0,
        60.0,
        60.0,
        20.0,
        16.7,
        100.0,
        100.0,
        100.0,
        100.0
      ],
      "avg": 75.67,
      "sample_duration": 0.10390830039978027
    },
    {
      "timestamp": 1763267684.85944,
      "process_cpu": 57.48,
      "process_cpu_raw": 574.8,
      "percpu": [
        100.0,
        83.3,
        83.3,
        71.4,
        60.0,
        50.0,
        100.0,
        100.0,
        100.0,
        100.0
      ],
      "avg": 84.8,
      "sample_duration": 0.11568689346313477
    },
    {
      "timestamp": 1763267685.2321768,
      "process_cpu": 58.33,
      "process_cpu_raw": 583.3,
      "percpu": [
        100.0,
        83.3,
        60.0,
        60.0,
        33.3,
        20.0,
        100.0,
        100.0,
        100.0,
        100.0
      ],
      "avg": 75.66,
      "sample_duration": 0.10924315452575684
    },
    {
      "timestamp": 1763267685.595087,
      "process_cpu": 57.970000000000006,
      "process_cpu_raw": 579.7,
      "percpu": [
        85.7,
        85.7,
        66.7,
        57.1,
        0.0,
        16.7,
        100.0,
        100.0,
        100.0,
        100.0
      ],
      "avg": 71.19,
      "sample_duration": 0.1163339614868164
    },
    {
      "timestamp": 1763267685.9632041,
      "process_cpu": 57.57000000000001,
      "process_cpu_raw": 575.7,
      "percpu": [
        100.0,
        83.3,
        83.3,
        80.0,
        50.0,
        50.0,
        100.0,
        100.0,
        100.0,
        100.0
      ],
      "avg": 84.66,
      "sample_duration": 0.11675071716308594
    },
    {
      "timestamp": 1763267686.335584,
      "process_cpu": 59.42,
      "process_cpu_raw": 594.2,
      "percpu": [
        100.0,
        100.0,
        0.0,
        0.0,
        0.0,
        0.0,
        100.0,
        100.0,
        100.0,
        100.0
      ],
      "avg": 60.0,
      "sample_duration": 0.10915708541870117
    },
    {
      "timestamp": 1763267686.699007,
      "process_cpu": 58.44,
      "process_cpu_raw": 584.4,
      "percpu": [
        83.3,
        83.3,
        33.3,
        16.7,
        0.0,
        33.3,
        100.0,
        100.0,
        100.0,
        100.0
      ],
      "avg": 64.99,
      "sample_duration": 0.11597490310668945
    },
    {
      "timestamp": 1763267687.074742,
      "process_cpu": 58.589999999999996,
      "process_cpu_raw": 585.9,
      "percpu": [
        100.0,
        100.0,
        71.4,
        33.3,
        28.6,
        0.0,
        100.0,
        100.0,
        100.0,
        100.0
      ],
      "avg": 73.33,
      "sample_duration": 0.12013101577758789
    },
    {
      "timestamp": 1763267687.454905,
      "process_cpu": 58.54,
      "process_cpu_raw": 585.4,
      "percpu": [
        100.0,
        85.7,
        66.7,
        57.1,
        50.0,
        16.7,
        100.0,
        100.0,
        100.0,
        100.0
      ],
      "avg": 77.62,
      "sample_duration": 0.11043381690979004
    },
    {
      "timestamp": 1763267687.825374,
      "process_cpu": 59.54,
      "process_cpu_raw": 595.4,
      "percpu": [
        83.3,
        100.0,
        83.3,
        75.0,
        40.0,
        40.0,
        100.0,
        100.0,
        100.0,
        100.0
      ],
      "avg": 82.16,
      "sample_duration": 0.11379218101501465
    },
    {
      "timestamp": 1763267688.199213,
      "process_cpu": 57.4,
      "process_cpu_raw": 574.0,
      "percpu": [
        100.0,
        83.3,
        100.0,
        100.0,
        100.0,
        80.0,
        100.0,
        100.0,
        100.0,
        100.0
      ],
      "avg": 96.33,
      "sample_duration": 0.1140129566192627
    },
    {
      "timestamp": 1763267688.568959,
      "process_cpu": 57.720000000000006,
      "process_cpu_raw": 577.2,
      "percpu": [
        83.3,
        100.0,
        75.0,
        80.0,
        60.0,
        60.0,
        100.0,
        100.0,
        100.0,
        100.0
      ],
      "avg": 85.83,
      "sample_duration": 0.11309409141540527
    },
    {
      "timestamp": 1763267688.939174,
      "process_cpu": 57.79,
      "process_cpu_raw": 577.9,
      "percpu": [
        100.0,
        85.7,
        60.0,
        66.7,
        33.3,
        16.7,
        100.0,
        100.0,
        100.0,
        100.0
      ],
      "avg": 76.24,
      "sample_duration": 0.1073310375213623
    },
    {
      "timestamp": 1763267689.2978718,
      "process_cpu": 58.25,
      "process_cpu_raw": 582.5,
      "percpu": [
        85.7,
        100.0,
        83.3,
        80.0,
        66.7,
        66.7,
        100.0,
        100.0,
        100.0,
        100.0
      ],
      "avg": 88.24,
      "sample_duration": 0.11836123466491699
    },
    {
      "timestamp": 1763267689.6742778,
      "process_cpu": 58.1,
      "process_cpu_raw": 581.0,
      "percpu": [
        100.0,
        83.3,
        71.4,
        60.0,
        33.3,
        16.7,
        100.0,
        100.0,
        100.0,
        100.0
      ],
      "avg": 76.47,
      "sample_duration": 0.11846613883972168
    },
    {
      "timestamp": 1763267690.0547688,
      "process_cpu": 57.75,
      "process_cpu_raw": 577.5,
      "percpu": [
        83.3,
        83.3,
        83.3,
        66.7,
        50.0,
        16.7,
        100.0,
        100.0,
        100.0,
        85.7
      ],
      "avg": 76.9,
      "sample_duration": 0.1203000545501709
    },
    {
      "timestamp": 1763267690.432958,
      "process_cpu": 58.81,
      "process_cpu_raw": 588.1,
      "percpu": [
        100.0,
        85.7,
        60.0,
        40.0,
        28.6,
        20.0,
        100.0,
        100.0,
        100.0,
        100.0
      ],
      "avg": 73.42999999999999,
      "sample_duration": 0.11580801010131836
    },
    {
      "timestamp": 1763267690.806598,
      "process_cpu": 59.1,
      "process_cpu_raw": 591.0,
      "percpu": [
        100.0,
        100.0,
        60.0,
        60.0,
        20.0,
        16.7,
        83.3,
        100.0,
        100.0,
        100.0
      ],
      "avg": 74.0,
      "sample_duration": 0.10951018333435059
    }
  ],
  "power": {
    "energy_joules": 119.94287738543748,
    "avg_power_w": 9.18475,
    "avg_temperature_c": null,
    "log_path": "/Users/chenxinzhe/Library/Mobile Documents/com~apple~CloudDocs/NUS/Project_CEG5003/P5003/results/power/powermetrics_ECDSA-P521_sign_6t_20251116-123437.log",
    "sample_count": 12,
    "samples": [
      {
        "power_w": 9.128,
        "timestamp": 1763267679.471106
      },
      {
        "power_w": 9.211,
        "timestamp": 1763267680.478482
      },
      {
        "power_w": 9.032,
        "timestamp": 1763267681.483743
      },
      {
        "power_w": 9.074,
        "timestamp": 1763267682.490237
      },
      {
        "power_w": 9.221,
        "timestamp": 1763267683.496497
      },
      {
        "power_w": 9.258,
        "timestamp": 1763267684.501774
      },
      {
        "power_w": 9.179,
        "timestamp": 1763267685.509364
      },
      {
        "power_w": 9.099,
        "timestamp": 1763267686.515867
      },
      {
        "power_w": 9.267,
        "timestamp": 1763267687.522669
      },
      {
        "power_w": 9.381,
        "timestamp": 1763267688.5296798
      },
      {
        "power_w": 9.266,
        "timestamp": 1763267689.5360699
      },
      {
        "power_w": 9.101,
        "timestamp": 1763267690.542681
      }
    ]
  }
}