{
  "cpu_samples": [
    {
      "timestamp": 1763115641.19226,
      "process_cpu": 96.52,
      "process_cpu_raw": 965.1999999999999,
      "percpu": [
        99.1,
        98.7,
        98.7,
        98.3,
        97.9,
        97.9,
        99.6,
        100.0,
        100.0,
        99.6
      ],
      "avg": 98.97999999999999
    },
    {
      "timestamp": 1763115642.176939,
      "process_cpu": 95.74999999999999,
      "process_cpu_raw": 957.4999999999999,
      "percpu": [
        100.0,
        100.0,
        100.0,
        100.0,
        100.0,
        100.0,
        100.0,
        100.0,
        100.0,
        100.0
      ],
      "avg": 100.0
    },
    {
      "timestamp": 1763115643.117541,
      "process_cpu": 104.73999999999998,
      "process_cpu_raw": 1047.3999999999999,
      "percpu": [
        100.0,
        100.0,
        100.0,
        100.0,
        100.0,
        100.0,
        100.0,
        100.0,
        100.0,
        100.0
      ],
      "avg": 100.0
    },
    {
      "timestamp": 1763115644.074721,
      "process_cpu": 94.36999999999999,
      "process_cpu_raw": 943.6999999999999,
      "percpu": [
        100.0,
        100.0,
        100.0,
        100.0,
        100.0,
        100.0,
        100.0,
        100.0,
        100.0,
        100.0
      ],
      "avg": 100.0
    },
    {
      "timestamp": 1763115645.020052,
      "process_cpu": 102.54,
      "process_cpu_raw": 1025.4,
      "percpu": [
        100.0,
        100.0,
        100.0,
        100.0,
        100.0,
        100.0,
        100.0,
        100.0,
        100.0,
        100.0
      ],
      "avg": 100.0
    },
    {
      "timestamp": 1763115645.973709,
      "process_cpu": 97.25999999999999,
      "process_cpu_raw": 972.5999999999999,
      "percpu": [
        100.0,
        100.0,
        100.0,
        100.0,
        100.0,
        100.0,
        100.0,
        100.0,
        100.0,
        100.0
      ],
      "avg": 100.0
    },
    {
      "timestamp": 1763115646.92793,
      "process_cpu": 95.00000000000001,
      "process_cpu_raw": 950.0000000000001,
      "percpu": [
        100.0,
        100.0,
        100.0,
        100.0,
        100.0,
        100.0,
        100.0,
        100.0,
        100.0,
        100.0
      ],
      "avg": 100.0
    },
    {
      "timestamp": 1763115647.88485,
      "process_cpu": 96.30000000000001,
      "process_cpu_raw": 963.0000000000001,
      "percpu": [
        100.0,
        100.0,
        100.0,
        100.0,
        100.0,
        100.0,
        100.0,
        100.0,
        100.0,
        100.0
      ],
      "avg": 100.0
    },
    {
      "timestamp": 1763115648.825168,
      "process_cpu": 92.61999999999999,
      "process_cpu_raw": 926.1999999999999,
      "percpu": [
        100.0,
        100.0,
        100.0,
        100.0,
        100.0,
        100.0,
        100.0,
        100.0,
        100.0,
        100.0
      ],
      "avg": 100.0
    },
    {
      "timestamp": 1763115649.786166,
      "process_cpu": 92.97,
      "process_cpu_raw": 929.7,
      "percpu": [
        100.0,
        100.0,
        100.0,
        100.0,
        100.0,
        100.0,
        100.0,
        100.0,
        100.0,
        100.0
      ],
      "avg": 100.0
    },
    {
      "timestamp": 1763115650.7522,
      "process_cpu": 89.80999999999999,
      "process_cpu_raw": 898.0999999999999,
      "percpu": [
        100.0,
        100.0,
        100.0,
        100.0,
        100.0,
        100.0,
        100.0,
        100.0,
        100.0,
        100.0
      ],
      "avg": 100.0
    },
    {
      "timestamp": 1763115651.723221,
      "process_cpu": 95.23,
      "process_cpu_raw": 952.3000000000001,
      "percpu": [
        100.0,
        100.0,
        100.0,
        100.0,
        100.0,
        100.0,
        100.0,
        100.0,
        100.0,
        100.0
      ],
      "avg": 100.0
    },
    {
      "timestamp": 1763115652.3854809,
      "process_cpu": 39.870000000000005,
      "process_cpu_raw": 398.70000000000005,
      "percpu": [
        98.5,
        97.0,
        98.5,
        95.5,
        93.9,
        94.1,
        88.2,
        88.2,
        88.2,
        89.6
      ],
      "avg": 93.17
    }
  ],
  "power": {
    "energy_joules": 124.26678185202859,
    "avg_power_w": 10.245818181818182,
    "avg_temperature_c": null,
    "log_path": "/Users/chenxinzhe/Library/Mobile Documents/com~apple~CloudDocs/NUS/Project_CEG5003/P5003/results/power/powermetrics_ECDSA-P384_sign_10t_20251114-182040.log",
    "sample_count": 11,
    "samples": [
      {
        "power_w": 9.724,
        "timestamp": 1763115642.186734
      },
      {
        "power_w": 9.981,
        "timestamp": 1763115643.194519
      },
      {
        "power_w": 10.187,
        "timestamp": 1763115644.19757
      },
      {
        "power_w": 10.303,
        "timestamp": 1763115645.20375
      },
      {
        "power_w": 10.344,
        "timestamp": 1763115646.210492
      },
      {
        "power_w": 10.387,
        "timestamp": 1763115647.2175539
      },
      {
        "power_w": 10.386,
        "timestamp": 1763115648.223799
      },
      {
        "power_w": 10.382,
        "timestamp": 1763115649.2304661
      },
      {
        "power_w": 10.386,
        "timestamp": 1763115650.237869
      },
      {
        "power_w": 10.314,
        "timestamp": 1763115651.2480772
      },
      {
        "power_w": 10.31,
        "timestamp": 1763115652.250229
      }
    ]
  }
}