{
  "cpu_samples": [
    {
      "timestamp": 1763268868.97053,
      "process_cpu": 58.54,
      "process_cpu_raw": 585.4,
      "percpu": [
        100.0,
        100.0,
        80.0,
        75.0,
        60.0,
        83.3,
        100.0,
        100.0,
        100.0,
        100.0
      ],
      "avg": 89.83,
      "sample_duration": 0.10554385185241699
    },
    {
      "timestamp": 1763268869.33111,
      "process_cpu": 60.57000000000001,
      "process_cpu_raw": 605.7,
      "percpu": [
        100.0,
        100.0,
        75.0,
        66.7,
        60.0,
        50.0,
        100.0,
        100.0,
        100.0,
        100.0
      ],
      "avg": 85.17,
      "sample_duration": 0.10503792762756348
    },
    {
      "timestamp": 1763268869.6896472,
      "process_cpu": 57.220000000000006,
      "process_cpu_raw": 572.2,
      "percpu": [
        100.0,
        100.0,
        83.3,
        100.0,
        80.0,
        66.7,
        100.0,
        100.0,
        100.0,
        100.0
      ],
      "avg": 93.0,
      "sample_duration": 0.10664176940917969
    },
    {
      "timestamp": 1763268870.048172,
      "process_cpu": 62.1,
      "process_cpu_raw": 621.0,
      "percpu": [
        83.3,
        83.3,
        75.0,
        60.0,
        40.0,
        40.0,
        100.0,
        100.0,
        100.0,
        100.0
      ],
      "avg": 78.16,
      "sample_duration": 0.10980987548828125
    },
    {
      "timestamp": 1763268870.413012,
      "process_cpu": 61.67999999999999,
      "process_cpu_raw": 616.8,
      "percpu": [
        83.3,
        100.0,
        80.0,
        50.0,
        40.0,
        20.0,
        100.0,
        100.0,
        100.0,
        100.0
      ],
      "avg": 77.33,
      "sample_duration": 0.11029386520385742
    },
    {
      "timestamp": 1763268870.778341,
      "process_cpu": 58.98,
      "process_cpu_raw": 589.8,
      "percpu": [
        83.3,
        75.0,
        83.3,
        60.0,
        33.3,
        25.0,
        100.0,
        100.0,
        100.0,
        100.0
      ],
      "avg": 75.99,
      "sample_duration": 0.10496807098388672
    },
    {
      "timestamp": 1763268871.155287,
      "process_cpu": 38.85,
      "process_cpu_raw": 388.5,
      "percpu": [
        100.0,
        100.0,
        100.0,
        100.0,
        100.0,
        100.0,
        100.0,
        100.0,
        100.0,
        100.0
      ],
      "avg": 100.0,
      "sample_duration": 0.1348280906677246
    },
    {
      "timestamp": 1763268871.545204,
      "process_cpu": 59.989999999999995,
      "process_cpu_raw": 599.9,
      "percpu": [
        100.0,
        100.0,
        100.0,
        100.0,
        100.0,
        100.0,
        100.0,
        100.0,
        100.0,
        100.0
      ],
      "avg": 100.0,
      "sample_duration": 0.10817623138427734
    },
    {
      "timestamp": 1763268871.9067361,
      "process_cpu": 56.870000000000005,
      "process_cpu_raw": 568.7,
      "percpu": [
        83.3,
        83.3,
        83.3,
        83.3,
        80.0,
        80.0,
        100.0,
        100.0,
        100.0,
        100.0
      ],
      "avg": 89.32000000000001,
      "sample_duration": 0.10804486274719238
    },
    {
      "timestamp": 1763268872.26819,
      "process_cpu": 35.58,
      "process_cpu_raw": 355.8,
      "percpu": [
        100.0,
        100.0,
        100.0,
        100.0,
        100.0,
        100.0,
        100.0,
        100.0,
        100.0,
        100.0
      ],
      "avg": 100.0,
      "sample_duration": 0.10641622543334961
    },
    {
      "timestamp": 1763268872.626823,
      "process_cpu": 59.73,
      "process_cpu_raw": 597.3,
      "percpu": [
        83.3,
        80.0,
        100.0,
        80.0,
        66.7,
        80.0,
        100.0,
        100.0,
        100.0,
        100.0
      ],
      "avg": 89.0,
      "sample_duration": 0.10567116737365723
    },
    {
      "timestamp": 1763268872.987523,
      "process_cpu": 59.279999999999994,
      "process_cpu_raw": 592.8,
      "percpu": [
        100.0,
        100.0,
        100.0,
        100.0,
        100.0,
        100.0,
        100.0,
        100.0,
        100.0,
        100.0
      ],
      "avg": 100.0,
      "sample_duration": 0.12096214294433594
    },
    {
      "timestamp": 1763268873.3588731,
      "process_cpu": 39.78,
      "process_cpu_raw": 397.8,
      "percpu": [
        100.0,
        100.0,
        100.0,
        100.0,
        100.0,
        100.0,
        100.0,
        100.0,
        100.0,
        100.0
      ],
      "avg": 100.0,
      "sample_duration": 0.12178897857666016
    },
    {
      "timestamp": 1763268873.735323,
      "process_cpu": 59.4,
      "process_cpu_raw": 594.0,
      "percpu": [
        85.7,
        83.3,
        66.7,
        75.0,
        66.7,
        40.0,
        100.0,
        100.0,
        100.0,
        100.0
      ],
      "avg": 81.74,
      "sample_duration": 0.1102449893951416
    },
    {
      "timestamp": 1763268874.098955,
      "process_cpu": 57.760000000000005,
      "process_cpu_raw": 577.6,
      "percpu": [
        100.0,
        100.0,
        100.0,
        83.3,
        83.3,
        83.3,
        100.0,
        100.0,
        100.0,
        100.0
      ],
      "avg": 94.99,
      "sample_duration": 0.1088261604309082
    },
    {
      "timestamp": 1763268874.462813,
      "process_cpu": 58.160000000000004,
      "process_cpu_raw": 581.6,
      "percpu": [
        80.0,
        83.3,
        83.3,
        66.7,
        20.0,
        20.0,
        100.0,
        100.0,
        100.0,
        100.0
      ],
      "avg": 75.33,
      "sample_duration": 0.10845613479614258
    },
    {
      "timestamp": 1763268874.826303,
      "process_cpu": 57.67999999999999,
      "process_cpu_raw": 576.8,
      "percpu": [
        80.0,
        100.0,
        85.7,
        71.4,
        60.0,
        33.3,
        100.0,
        100.0,
        100.0,
        100.0
      ],
      "avg": 83.03999999999999,
      "sample_duration": 0.10548996925354004
    },
    {
      "timestamp": 1763268875.1830678,
      "process_cpu": 58.9,
      "process_cpu_raw": 589.0,
      "percpu": [
        80.0,
        100.0,
        80.0,
        66.7,
        50.0,
        42.9,
        100.0,
        100.0,
        100.0,
        100.0
      ],
      "avg": 81.96000000000001,
      "sample_duration": 0.10443615913391113
    },
    {
      "timestamp": 1763268875.5425332,
      "process_cpu": 58.94,
      "process_cpu_raw": 589.4,
      "percpu": [
        100.0,
        100.0,
        60.0,
        25.0,
        50.0,
        0.0,
        100.0,
        100.0,
        100.0,
        100.0
      ],
      "avg": 73.5,
      "sample_duration": 0.10992574691772461
    },
    {
      "timestamp": 1763268875.9062872,
      "process_cpu": 61.010000000000005,
      "process_cpu_raw": 610.1,
      "percpu": [
        80.0,
        71.4,
        83.3,
        60.0,
        0.0,
        0.0,
        100.0,
        100.0,
        100.0,
        100.0
      ],
      "avg": 69.47,
      "sample_duration": 0.11025166511535645
    },
    {
      "timestamp": 1763268876.2715771,
      "process_cpu": 61.06,
      "process_cpu_raw": 610.6,
      "percpu": [
        100.0,
        100.0,
        100.0,
        60.0,
        60.0,
        60.0,
        100.0,
        100.0,
        100.0,
        100.0
      ],
      "avg": 88.0,
      "sample_duration": 0.10566306114196777
    },
    {
      "timestamp": 1763268876.632267,
      "process_cpu": 59.64,
      "process_cpu_raw": 596.4,
      "percpu": [
        85.7,
        87.5,
        80.0,
        80.0,
        33.3,
        20.0,
        100.0,
        100.0,
        100.0,
        100.0
      ],
      "avg": 78.65,
      "sample_duration": 0.1088109016418457
    },
    {
      "timestamp": 1763268876.9961169,
      "process_cpu": 59.23,
      "process_cpu_raw": 592.3,
      "percpu": [
        100.0,
        100.0,
        71.4,
        75.0,
        57.1,
        40.0,
        100.0,
        100.0,
        100.0,
        100.0
      ],
      "avg": 84.35,
      "sample_duration": 0.10652804374694824
    },
    {
      "timestamp": 1763268877.354292,
      "process_cpu": 59.15,
      "process_cpu_raw": 591.5,
      "percpu": [
        100.0,
        100.0,
        66.7,
        60.0,
        40.0,
        16.7,
        100.0,
        100.0,
        100.0,
        100.0
      ],
      "avg": 78.34,
      "sample_duration": 0.10986804962158203
    },
    {
      "timestamp": 1763268877.718118,
      "process_cpu": 57.42999999999999,
      "process_cpu_raw": 574.3,
      "percpu": [
        85.7,
        100.0,
        75.0,
        60.0,
        50.0,
        42.9,
        100.0,
        100.0,
        100.0,
        100.0
      ],
      "avg": 81.36,
      "sample_duration": 0.10951423645019531
    },
    {
      "timestamp": 1763268878.078198,
      "process_cpu": 60.46,
      "process_cpu_raw": 604.6,
      "percpu": [
        83.3,
        83.3,
        83.3,
        100.0,
        75.0,
        66.7,
        100.0,
        100.0,
        100.0,
        100.0
      ],
      "avg": 89.16,
      "sample_duration": 0.10663819313049316
    },
    {
      "timestamp": 1763268878.439858,
      "process_cpu": 56.9,
      "process_cpu_raw": 569.0,
      "percpu": [
        83.3,
        83.3,
        66.7,
        60.0,
        40.0,
        20.0,
        100.0,
        100.0,
        100.0,
        100.0
      ],
      "avg": 75.33,
      "sample_duration": 0.10765409469604492
    },
    {
      "timestamp": 1763268878.80203,
      "process_cpu": 58.73,
      "process_cpu_raw": 587.3,
      "percpu": [
        100.0,
        83.3,
        80.0,
        50.0,
        20.0,
        40.0,
        100.0,
        100.0,
        100.0,
        100.0
      ],
      "avg": 77.33,
      "sample_duration": 0.11026883125305176
    },
    {
      "timestamp": 1763268879.167331,
      "process_cpu": 59.089999999999996,
      "process_cpu_raw": 590.9,
      "percpu": [
        83.3,
        100.0,
        80.0,
        60.0,
        20.0,
        33.3,
        100.0,
        100.0,
        100.0,
        100.0
      ],
      "avg": 77.66,
      "sample_duration": 0.10593605041503906
    },
    {
      "timestamp": 1763268879.5243678,
      "process_cpu": 59.86,
      "process_cpu_raw": 598.6,
      "percpu": [
        80.0,
        80.0,
        83.3,
        83.3,
        60.0,
        71.4,
        100.0,
        100.0,
        100.0,
        100.0
      ],
      "avg": 85.8,
      "sample_duration": 0.10959219932556152
    },
    {
      "timestamp": 1763268879.887095,
      "process_cpu": 62.0,
      "process_cpu_raw": 620.0,
      "percpu": [
        100.0,
        100.0,
        100.0,
        100.0,
        83.3,
        100.0,
        100.0,
        100.0,
        100.0,
        100.0
      ],
      "avg": 98.33,
      "sample_duration": 0.10598111152648926
    },
    {
      "timestamp": 1763268880.248105,
      "process_cpu": 57.44,
      "process_cpu_raw": 574.4,
      "percpu": [
        83.3,
        83.3,
        75.0,
        83.3,
        66.7,
        50.0,
        100.0,
        100.0,
        100.0,
        100.0
      ],
      "avg": 84.16,
      "sample_duration": 0.10758590698242188
    },
    {
      "timestamp": 1763268880.61072,
      "process_cpu": 59.19,
      "process_cpu_raw": 591.9,
      "percpu": [
        100.0,
        100.0,
        66.7,
        50.0,
        28.6,
        16.7,
        100.0,
        100.0,
        100.0,
        100.0
      ],
      "avg": 76.2,
      "sample_duration": 0.10866689682006836
    },
    {
      "timestamp": 1763268880.974423,
      "process_cpu": 56.05,
      "process_cpu_raw": 560.5,
      "percpu": [
        100.0,
        80.0,
        80.0,
        66.7,
        83.3,
        66.7,
        100.0,
        100.0,
        100.0,
        100.0
      ],
      "avg": 87.67,
      "sample_duration": 0.10689425468444824
    },
    {
      "timestamp": 1763268881.336343,
      "process_cpu": 59.5,
      "process_cpu_raw": 595.0,
      "percpu": [
        83.3,
        100.0,
        71.4,
        60.0,
        60.0,
        42.9,
        100.0,
        100.0,
        100.0,
        100.0
      ],
      "avg": 81.76,
      "sample_duration": 0.10869097709655762
    },
    {
      "timestamp": 1763268881.697273,
      "process_cpu": 22.96,
      "process_cpu_raw": 229.6,
      "percpu": [
        66.7,
        57.1,
        20.0,
        16.7,
        16.7,
        16.7,
        0.0,
        0.0,
        0.0,
        0.0
      ],
      "avg": 19.39,
      "sample_duration": 0.11026215553283691
    }
  ],
  "power": {
    "energy_joules": 96.87132533860208,
    "avg_power_w": 7.368833333333334,
    "avg_temperature_c": null,
    "log_path": "/Users/chenxinzhe/Library/Mobile Documents/com~apple~CloudDocs/NUS/Project_CEG5003/P5003/results/power/powermetrics_SPHINCS+-SHA2-128s-simple_verify_6t_20251116-125428.log",
    "sample_count": 12,
    "samples": [
      {
        "power_w": 6.8,
        "timestamp": 1763268870.282836
      },
      {
        "power_w": 8.675,
        "timestamp": 1763268871.286874
      },
      {
        "power_w": 7.709,
        "timestamp": 1763268872.292338
      },
      {
        "power_w": 7.024,
        "timestamp": 1763268873.297703
      },
      {
        "power_w": 6.301,
        "timestamp": 1763268874.302423
      },
      {
        "power_w": 6.984,
        "timestamp": 1763268875.307102
      },
      {
        "power_w": 7.547,
        "timestamp": 1763268876.311923
      },
      {
        "power_w": 8.129,
        "timestamp": 1763268877.316727
      },
      {
        "power_w": 7.375,
        "timestamp": 1763268878.3216472
      },
      {
        "power_w": 7.506,
        "timestamp": 1763268879.326325
      },
      {
        "power_w": 7.445,
        "timestamp": 1763268880.331257
      },
      {
        "power_w": 6.931,
        "timestamp": 1763268881.336093
      }
    ]
  }
}