{
  "cpu_samples": [
    {
      "timestamp": 1763117381.013108,
      "process_cpu": 90.63,
      "process_cpu_raw": 906.3,
      "percpu": [
        93.0,
        91.2,
        83.0,
        80.7,
        70.4,
        58.5,
        99.1,
        99.1,
        99.6,
        98.7
      ],
      "avg": 87.33
    },
    {
      "timestamp": 1763117381.8111129,
      "process_cpu": 80.33999999999999,
      "process_cpu_raw": 803.3999999999999,
      "percpu": [
        93.7,
        93.8,
        91.3,
        83.7,
        51.9,
        50.0,
        100.0,
        100.0,
        100.0,
        100.0
      ],
      "avg": 86.44
    },
    {
      "timestamp": 1763117382.610144,
      "process_cpu": 78.03,
      "process_cpu_raw": 780.3000000000001,
      "percpu": [
        93.7,
        94.9,
        93.7,
        86.2,
        32.5,
        25.0,
        100.0,
        100.0,
        100.0,
        100.0
      ],
      "avg": 82.6
    },
    {
      "timestamp": 1763117383.42382,
      "process_cpu": 81.0,
      "process_cpu_raw": 810.0,
      "percpu": [
        96.3,
        97.5,
        96.3,
        96.3,
        72.0,
        75.3,
        100.0,
        100.0,
        100.0,
        100.0
      ],
      "avg": 93.37
    },
    {
      "timestamp": 1763117384.223779,
      "process_cpu": 81.08,
      "process_cpu_raw": 810.8,
      "percpu": [
        96.3,
        97.5,
        96.3,
        96.3,
        82.3,
        76.5,
        100.0,
        100.0,
        100.0,
        100.0
      ],
      "avg": 94.52000000000001
    },
    {
      "timestamp": 1763117385.0414531,
      "process_cpu": 79.38999999999999,
      "process_cpu_raw": 793.8999999999999,
      "percpu": [
        95.0,
        98.8,
        96.3,
        97.5,
        85.5,
        82.7,
        100.0,
        100.0,
        100.0,
        100.0
      ],
      "avg": 95.58
    },
    {
      "timestamp": 1763117385.849293,
      "process_cpu": 78.92999999999999,
      "process_cpu_raw": 789.3,
      "percpu": [
        90.2,
        95.1,
        93.8,
        90.1,
        65.8,
        64.2,
        100.0,
        100.0,
        100.0,
        100.0
      ],
      "avg": 89.92
    },
    {
      "timestamp": 1763117386.654955,
      "process_cpu": 74.21,
      "process_cpu_raw": 742.0999999999999,
      "percpu": [
        97.5,
        97.5,
        98.7,
        93.9,
        76.8,
        76.2,
        100.0,
        100.0,
        100.0,
        100.0
      ],
      "avg": 94.06
    },
    {
      "timestamp": 1763117387.4535491,
      "process_cpu": 76.35,
      "process_cpu_raw": 763.5,
      "percpu": [
        97.5,
        97.5,
        93.8,
        91.1,
        74.7,
        68.7,
        100.0,
        100.0,
        100.0,
        100.0
      ],
      "avg": 92.33
    },
    {
      "timestamp": 1763117388.255286,
      "process_cpu": 78.38,
      "process_cpu_raw": 783.8,
      "percpu": [
        97.5,
        94.9,
        91.4,
        87.3,
        34.6,
        31.3,
        100.0,
        100.0,
        100.0,
        100.0
      ],
      "avg": 83.7
    },
    {
      "timestamp": 1763117389.056823,
      "process_cpu": 83.37,
      "process_cpu_raw": 833.7,
      "percpu": [
        96.2,
        96.3,
        95.0,
        87.7,
        29.1,
        21.5,
        100.0,
        100.0,
        100.0,
        100.0
      ],
      "avg": 82.58
    },
    {
      "timestamp": 1763117389.859643,
      "process_cpu": 78.55,
      "process_cpu_raw": 785.5,
      "percpu": [
        95.0,
        95.1,
        92.4,
        83.7,
        47.5,
        34.6,
        100.0,
        100.0,
        100.0,
        100.0
      ],
      "avg": 84.83
    },
    {
      "timestamp": 1763117390.663666,
      "process_cpu": 80.35,
      "process_cpu_raw": 803.5,
      "percpu": [
        95.1,
        96.3,
        95.1,
        90.0,
        62.5,
        54.3,
        100.0,
        100.0,
        100.0,
        100.0
      ],
      "avg": 89.33
    },
    {
      "timestamp": 1763117391.4611251,
      "process_cpu": 81.44000000000001,
      "process_cpu_raw": 814.4000000000001,
      "percpu": [
        94.9,
        88.6,
        91.2,
        88.8,
        49.4,
        40.0,
        100.0,
        100.0,
        100.0,
        100.0
      ],
      "avg": 85.28999999999999
    },
    {
      "timestamp": 1763117392.261112,
      "process_cpu": 82.05000000000001,
      "process_cpu_raw": 820.5000000000001,
      "percpu": [
        93.8,
        93.8,
        90.0,
        85.0,
        37.2,
        32.9,
        100.0,
        100.0,
        100.0,
        100.0
      ],
      "avg": 83.27000000000001
    }
  ],
  "power": {
    "energy_joules": 108.85811565364492,
    "avg_power_w": 9.019181818181819,
    "avg_temperature_c": null,
    "log_path": "/Users/chenxinzhe/Library/Mobile Documents/com~apple~CloudDocs/NUS/Project_CEG5003/P5003/results/power/powermetrics_SPHINCS+-SHA2-256f-simple_sign_8t_20251114-184940.log",
    "sample_count": 11,
    "samples": [
      {
        "power_w": 8.569,
        "timestamp": 1763117382.06448
      },
      {
        "power_w": 9.034,
        "timestamp": 1763117383.070854
      },
      {
        "power_w": 9.052,
        "timestamp": 1763117384.077164
      },
      {
        "power_w": 9.055,
        "timestamp": 1763117385.082316
      },
      {
        "power_w": 8.912,
        "timestamp": 1763117386.08865
      },
      {
        "power_w": 8.964,
        "timestamp": 1763117387.0938702
      },
      {
        "power_w": 8.729,
        "timestamp": 1763117388.107029
      },
      {
        "power_w": 8.955,
        "timestamp": 1763117389.106118
      },
      {
        "power_w": 9.237,
        "timestamp": 1763117390.111945
      },
      {
        "power_w": 9.344,
        "timestamp": 1763117391.117719
      },
      {
        "power_w": 9.36,
        "timestamp": 1763117392.123507
      }
    ]
  }
}